{"AAE18D":{"date":"21 April 2021","day":"Wednesday","time":"1.00 pm","code":"AAE18D","name":"EXPLORING THE WORDS & SOUNDS OF ENGLISH","duration":"2 hr 30 min"},"SS9610":{"date":"21 April 2021","day":"Wednesday","time":"1.00 pm","code":"SS9610","name":"FUNDAMENTALS OF SPORT INJURIES","duration":"2 hr 30 min"},"SS9604":{"date":"22 April 2021","day":"Thursday","time":"9.00 am","code":"SS9604","name":"FOUNDATIONS OF EXERCISE PHYSIOLOGY","duration":"2 hr 30 min"},"AAM33E":{"date":"22 April 2021","day":"Thursday","time":"1.00 pm","code":"AAM33E","name":"MODERN ALGEBRA","duration":"2 hr 30 min"},"AGQ28B":{"date":"22 April 2021","day":"Thursday","time":"1.00 pm","code":"AGQ28B","name":"EVERYDAY SCIENCE IN FOODS","duration":"2 hr 30 min"},"AAB20D":{"date":"23 April 2021","day":"Friday","time":"9.00 am","code":"AAB20D","name":"ECOLOGY","duration":"2 hr 30 min"},"AAE28D":{"date":"23 April 2021","day":"Friday","time":"9.00 am","code":"AAE28D","name":"LANGUAGE ACQUISITION & DEVELOPMENT","duration":"2 hr 30 min"},"AAQ10A":{"date":"23 April 2021","day":"Friday","time":"9.00 am","code":"AAQ10A","name":"PRINCIPLES OF NUTRITION","duration":"2 hr 30 min"},"AC1103":{"date":"23 April 2021","day":"Friday","time":"9.00 am","code":"AC1103","name":"ACCOUNTING I","duration":"2 hr 30 min"},"BA2204":{"date":"23 April 2021","day":"Friday","time":"9.00 am","code":"BA2204","name":"MODELS","duration":"3 hr"},"BF3204":{"date":"23 April 2021","day":"Friday","time":"9.00 am","code":"BF3204","name":"FINANCIAL MODELLING","duration":"2 hr"},"BS2105":{"date":"23 April 2021","day":"Friday","time":"9.00 am","code":"BS2105","name":"EMPEROR'S CANON OF INTERNAL MEDICINE","duration":"2 hr 30 min"},"BS3013":{"date":"23 April 2021","day":"Friday","time":"9.00 am","code":"BS3013","name":"DRUG DISCOVERY & DEVELOPMENT BIOTECHNOLOGY","duration":"2 hr 30 min"},"CE2006":{"date":"23 April 2021","day":"Friday","time":"9.00 am","code":"CE2006","name":"SOFTWARE ENGINEERING","duration":"2 hr"},"CE4001":{"date":"23 April 2021","day":"Friday","time":"9.00 am","code":"CE4001","name":"VIRTUAL & AUGMENTED REALITY","duration":"2 hr"},"CH2112":{"date":"23 April 2021","day":"Friday","time":"9.00 am","code":"CH2112","name":"CHEMICAL REACTION ENGINEERING","duration":"2 hr"},"CH3102":{"date":"23 April 2021","day":"Friday","time":"9.00 am","code":"CH3102","name":"CHEMICAL REACTION ENGINEERING","duration":"2 hr 30 min"},"CM3021":{"date":"23 April 2021","day":"Friday","time":"9.00 am","code":"CM3021","name":"ORGANOMETALLIC CHEMISTRY","duration":"2 hr"},"CV2016":{"date":"23 April 2021","day":"Friday","time":"9.00 am","code":"CV2016","name":"HYDROLOGY","duration":"2 hr 30 min"},"CZ2006":{"date":"23 April 2021","day":"Friday","time":"9.00 am","code":"CZ2006","name":"SOFTWARE ENGINEERING","duration":"2 hr"},"CZ4001":{"date":"23 April 2021","day":"Friday","time":"9.00 am","code":"CZ4001","name":"VIRTUAL & AUGMENTED REALITY","duration":"2 hr"},"EE1002":{"date":"23 April 2021","day":"Friday","time":"9.00 am","code":"EE1002","name":"PHYSICS FOUNDATION FOR ELECTRICAL & ELECTRONIC ENGINEERING","duration":"2 hr 30 min"},"ES2303":{"date":"23 April 2021","day":"Friday","time":"9.00 am","code":"ES2303","name":"INTRODUCTION TO ECOLOGY","duration":"2 hr"},"HE4003":{"date":"23 April 2021","day":"Friday","time":"9.00 am","code":"HE4003","name":"ADVANCED INTERNATIONAL FINANCE","duration":"2 hr 30 min"},"HL1003":{"date":"23 April 2021","day":"Friday","time":"9.00 am","code":"HL1003","name":"SURVEY OF ENGLISH LITERATURE II","duration":"2 hr 30 min"},"HS2002":{"date":"23 April 2021","day":"Friday","time":"9.00 am","code":"HS2002","name":"DOING SOCIAL RESEARCH","duration":"2 hr 30 min"},"MA4002":{"date":"23 April 2021","day":"Friday","time":"9.00 am","code":"MA4002","name":"FLUID DYNAMICS","duration":"2 hr 30 min"},"MS1016":{"date":"23 April 2021","day":"Friday","time":"9.00 am","code":"MS1016","name":"THERMODYNAMICS OF MATERIALS","duration":"2 hr"},"MS4014":{"date":"23 April 2021","day":"Friday","time":"9.00 am","code":"MS4014","name":"NANOMATERIALS: FUNDAMENTALS & APPLICATIONS","duration":"2 hr"},"AB3601":{"date":"23 April 2021","day":"Friday","time":"2.30 pm","code":"AB3601","name":"STRATEGIC MANAGEMENT","duration":"2 hr"},"BS2004":{"date":"23 April 2021","day":"Friday","time":"2.30 pm","code":"BS2004","name":"MOLECULAR & CELL BIOLOGY II","duration":"2 hr 30 min"},"CH4223":{"date":"23 April 2021","day":"Friday","time":"2.30 pm","code":"CH4223","name":"PETROLEUM REFINING","duration":"2 hr 30 min"},"CY1307":{"date":"23 April 2021","day":"Friday","time":"2.30 pm","code":"CY1307","name":"RELATIVITY & QUANTUM PHYSICS","duration":"2 hr 30 min"},"CZ3005":{"date":"23 April 2021","day":"Friday","time":"2.30 pm","code":"CZ3005","name":"ARTIFICIAL INTELLIGENCE","duration":"2 hr"},"EE2003":{"date":"23 April 2021","day":"Friday","time":"2.30 pm","code":"EE2003","name":"SEMICONDUCTOR FUNDAMENTALS","duration":"2 hr 30 min"},"EE4344":{"date":"23 April 2021","day":"Friday","time":"2.30 pm","code":"EE4344","name":"ANALYSIS & DESIGN OF INTEGRATED CIRCUITS","duration":"2 hr"},"EE4497":{"date":"23 April 2021","day":"Friday","time":"2.30 pm","code":"EE4497","name":"PATTERN RECOGNITION & MACHINE LEARNING","duration":"2 hr"},"EE4904":{"date":"23 April 2021","day":"Friday","time":"2.30 pm","code":"EE4904","name":"BIOMEDICAL INSTRUMENTATION","duration":"2 hr"},"EM9101":{"date":"23 April 2021","day":"Friday","time":"2.30 pm","code":"EM9101","name":"ENVIRONMENTAL QUALITY","duration":"2 hr 30 min"},"HC2010":{"date":"23 April 2021","day":"Friday","time":"2.30 pm","code":"HC2010","name":"CLASSICAL CHINESE FICTION","duration":"2 hr 30 min"},"HE1005":{"date":"23 April 2021","day":"Friday","time":"2.30 pm","code":"HE1005","name":"INTRODUCTION TO PROBABILITY & STATISTICAL INFERENCE","duration":"2 hr 30 min"},"HE3003":{"date":"23 April 2021","day":"Friday","time":"2.30 pm","code":"HE3003","name":"THE CHINESE ECONOMY","duration":"1 hr 30 min"},"HL2007":{"date":"23 April 2021","day":"Friday","time":"2.30 pm","code":"HL2007","name":"CONTEMPORARY LITERATURE & CULTURE","duration":"2 hr 30 min"},"MA2006":{"date":"23 April 2021","day":"Friday","time":"2.30 pm","code":"MA2006","name":"ENGINEERING MATHEMATICS","duration":"2 hr 30 min"},"MH3700":{"date":"23 April 2021","day":"Friday","time":"2.30 pm","code":"MH3700","name":"NUMERICAL ANALYSIS I","duration":"2 hr"},"MS3014":{"date":"23 April 2021","day":"Friday","time":"2.30 pm","code":"MS3014","name":"ANALYSIS OF MATERIALS","duration":"2 hr"},"PH1107":{"date":"23 April 2021","day":"Friday","time":"2.30 pm","code":"PH1107","name":"RELATIVITY & QUANTUM PHYSICS","duration":"2 hr 30 min"},"RE1017":{"date":"23 April 2021","day":"Friday","time":"2.30 pm","code":"RE1017","name":"INTRODUCTION TO ENGINEERING MECHANICS","duration":"2 hr 30 min"},"AC1104":{"date":"26 April 2021","day":"Monday","time":"9.00 am","code":"AC1104","name":"ACCOUNTING II","duration":"2 hr 30 min"},"BA3202":{"date":"26 April 2021","day":"Monday","time":"9.00 am","code":"BA3202","name":"ACTUARIAL STATISTICS","duration":"3 hr"},"BF2207":{"date":"26 April 2021","day":"Monday","time":"9.00 am","code":"BF2207","name":"INTERNATIONAL FINANCE","duration":"2 hr"},"BG2142":{"date":"26 April 2021","day":"Monday","time":"9.00 am","code":"BG2142","name":"BIOLOGICAL THERMODYNAMICS","duration":"2 hr 30 min"},"BS3104":{"date":"26 April 2021","day":"Monday","time":"9.00 am","code":"BS3104","name":"PATHOLOGY","duration":"2 hr 30 min"},"CE4034":{"date":"26 April 2021","day":"Monday","time":"9.00 am","code":"CE4034","name":"INFORMATION RETRIEVAL","duration":"2 hr"},"CM2031":{"date":"26 April 2021","day":"Monday","time":"9.00 am","code":"CM2031","name":"ORGANIC & BIOORGANIC CHEMISTRY","duration":"2 hr"},"CV2019":{"date":"26 April 2021","day":"Monday","time":"9.00 am","code":"CV2019","name":"MATRIX ALGEBRA & COMPUTATIONAL METHODS","duration":"2 hr 30 min"},"CZ4034":{"date":"26 April 2021","day":"Monday","time":"9.00 am","code":"CZ4034","name":"INFORMATION RETRIEVAL","duration":"2 hr"},"EE3017":{"date":"26 April 2021","day":"Monday","time":"9.00 am","code":"EE3017","name":"COMPUTER COMMUNICATIONS","duration":"2 hr"},"EE4273":{"date":"26 April 2021","day":"Monday","time":"9.00 am","code":"EE4273","name":"DIGITAL CONTROL SYSTEMS","duration":"2 hr"},"EN4102":{"date":"26 April 2021","day":"Monday","time":"9.00 am","code":"EN4102","name":"MEMBRANE WATER RECLAMATION TECHNOLOGY","duration":"2 hr 30 min"},"HA1003":{"date":"26 April 2021","day":"Monday","time":"9.00 am","code":"HA1003","name":"INTRODUCTION TO PUBLIC ADMINISTRATION","duration":"2 hr 30 min"},"HE2020":{"date":"26 April 2021","day":"Monday","time":"9.00 am","code":"HE2020","name":"SURVEY METHODS & SAMPLING TECHNIQUES","duration":"2 hr 30 min"},"IM2003":{"date":"26 April 2021","day":"Monday","time":"9.00 am","code":"IM2003","name":"COMPUTER COMMUNICATIONS","duration":"2 hr"},"MA3001":{"date":"26 April 2021","day":"Monday","time":"9.00 am","code":"MA3001","name":"MACHINE ELEMENT DESIGN","duration":"2 hr 30 min"},"MH1811":{"date":"26 April 2021","day":"Monday","time":"9.00 am","code":"MH1811","name":"MATHEMATICS 2","duration":"2 hr"},"MH3100":{"date":"26 April 2021","day":"Monday","time":"9.00 am","code":"MH3100","name":"REAL ANALYSIS I","duration":"2 hr"},"MS2015":{"date":"26 April 2021","day":"Monday","time":"9.00 am","code":"MS2015","name":"MECHANICAL BEHAVIOUR OF MATERIALS","duration":"2 hr"},"SS9602":{"date":"26 April 2021","day":"Monday","time":"9.00 am","code":"SS9602","name":"INTRODUCTION TO GROWTH & MOTOR DEVELOPMENT","duration":"2 hr 30 min"},"AC2105":{"date":"26 April 2021","day":"Monday","time":"1.00 pm","code":"AC2105","name":"ACCOUNTING FOR DECISION MAKING & CONTROL","duration":"2 hr 30 min"},"BA2201":{"date":"26 April 2021","day":"Monday","time":"1.00 pm","code":"BA2201","name":"ACTUARIAL ECONOMICS","duration":"2 hr 30 min"},"BS1005":{"date":"26 April 2021","day":"Monday","time":"1.00 pm","code":"BS1005","name":"BIOCHEMISTRY I","duration":"2 hr 30 min"},"BS3106":{"date":"26 April 2021","day":"Monday","time":"1.00 pm","code":"BS3106","name":"SEASONAL FEBRILE DISEASES","duration":"2 hr 30 min"},"CE3001":{"date":"26 April 2021","day":"Monday","time":"1.00 pm","code":"CE3001","name":"ADVANCED COMPUTER ARCHITECTURE","duration":"2 hr"},"CM1051":{"date":"26 April 2021","day":"Monday","time":"1.00 pm","code":"CM1051","name":"BASIC BIOLOGY & BIOCHEMISTRY","duration":"2 hr 30 min"},"CZ1016":{"date":"26 April 2021","day":"Monday","time":"1.00 pm","code":"CZ1016","name":"INTRODUCTION TO DATA SCIENCE","duration":"2 hr"},"CZ3001":{"date":"26 April 2021","day":"Monday","time":"1.00 pm","code":"CZ3001","name":"ADVANCED COMPUTER ARCHITECTURE","duration":"2 hr"},"EE2010":{"date":"26 April 2021","day":"Monday","time":"1.00 pm","code":"EE2010","name":"SIGNALS & SYSTEMS","duration":"2 hr 30 min"},"EE4694":{"date":"26 April 2021","day":"Monday","time":"1.00 pm","code":"EE4694","name":"IC RELIABILITY & FAILURE ANALYSIS","duration":"2 hr"},"HA4006":{"date":"26 April 2021","day":"Monday","time":"1.00 pm","code":"HA4006","name":"PUBLIC LEADERSHIP","duration":"2 hr 30 min"},"HH1003":{"date":"26 April 2021","day":"Monday","time":"1.00 pm","code":"HH1003","name":"ASIA-PACIFIC IN GLOBAL HISTORY: FROM 1800","duration":"2 hr 30 min"},"HS2003":{"date":"26 April 2021","day":"Monday","time":"1.00 pm","code":"HS2003","name":"ECONOMY & SOCIETY","duration":"2 hr 30 min"},"IM2004":{"date":"26 April 2021","day":"Monday","time":"1.00 pm","code":"IM2004","name":"SIGNALS & SYSTEMS","duration":"2 hr 30 min"},"MA2007":{"date":"26 April 2021","day":"Monday","time":"1.00 pm","code":"MA2007","name":"THERMODYNAMICS","duration":"2 hr 30 min"},"MH1301":{"date":"26 April 2021","day":"Monday","time":"1.00 pm","code":"MH1301","name":"DISCRETE MATHEMATICS","duration":"2 hr"},"MS4603":{"date":"26 April 2021","day":"Monday","time":"1.00 pm","code":"MS4603","name":"MICROELECTRONICS PROCESS INTEGRATION","duration":"2 hr"},"PH4508":{"date":"26 April 2021","day":"Monday","time":"1.00 pm","code":"PH4508","name":"INTRODUCTION TO GENERAL RELATIVITY","duration":"2 hr 30 min"},"MT0002":{"date":"26 April 2021","day":"Monday","time":"5.00 pm","code":"MT0002","name":"PROFESSIONALS IN SOCIETY","duration":"2 hr 30 min"},"AC3103":{"date":"27 April 2021","day":"Tuesday","time":"9.00 am","code":"AC3103","name":"ACCOUNTING ANALYSIS & EQUITY VALUATION","duration":"2 hr 30 min"},"BS2012":{"date":"27 April 2021","day":"Tuesday","time":"9.00 am","code":"BS2012","name":"GENETICS & GENOMICS","duration":"2 hr"},"CE2003":{"date":"27 April 2021","day":"Tuesday","time":"9.00 am","code":"CE2003","name":"DIGITAL SYSTEMS DESIGN","duration":"2 hr"},"CM3041":{"date":"27 April 2021","day":"Tuesday","time":"9.00 am","code":"CM3041","name":"PHYSICAL & BIOPHYSICAL CHEMISTRY 2","duration":"2 hr"},"CS2021":{"date":"27 April 2021","day":"Tuesday","time":"9.00 am","code":"CS2021","name":"NEWS REPORTING & WRITING","duration":"2 hr"},"CV2012":{"date":"27 April 2021","day":"Tuesday","time":"9.00 am","code":"CV2012","name":"STRUCTURAL ANALYSIS II","duration":"2 hr 30 min"},"EE2007":{"date":"27 April 2021","day":"Tuesday","time":"9.00 am","code":"EE2007","name":"ENGINEERING MATHEMATICS II","duration":"2 hr 30 min"},"EE4490":{"date":"27 April 2021","day":"Tuesday","time":"9.00 am","code":"EE4490","name":"MULTIMEDIA SYSTEMS","duration":"2 hr"},"EE4530":{"date":"27 April 2021","day":"Tuesday","time":"9.00 am","code":"EE4530","name":"POWER SYSTEM ANALYSIS & CONTROL","duration":"2 hr"},"EE4645":{"date":"27 April 2021","day":"Tuesday","time":"9.00 am","code":"EE4645","name":"MICROFABRICATION ENGINEERING","duration":"2 hr"},"EN0001":{"date":"27 April 2021","day":"Tuesday","time":"9.00 am","code":"EN0001","name":"SUSTAINABILITY PRACTICES FOR URBAN & MARINE ENVIRONMENT","duration":"2 hr 30 min"},"HA2004":{"date":"27 April 2021","day":"Tuesday","time":"9.00 am","code":"HA2004","name":"THEORIES IN INTERNATIONAL RELATIONS","duration":"2 hr 30 min"},"HE3016":{"date":"27 April 2021","day":"Tuesday","time":"9.00 am","code":"HE3016","name":"PRINCIPLES OF MATHEMATICS FINANCE","duration":"2 hr 30 min"},"HL1005":{"date":"27 April 2021","day":"Tuesday","time":"9.00 am","code":"HL1005","name":"INTRODUCTION TO SINGAPORE LITERATURE","duration":"2 hr 30 min"},"HL4009":{"date":"27 April 2021","day":"Tuesday","time":"9.00 am","code":"HL4009","name":"POPULAR LITERATURE & CULTURE","duration":"2 hr 30 min"},"HS3018":{"date":"27 April 2021","day":"Tuesday","time":"9.00 am","code":"HS3018","name":"SOCIOLOGY OF GENDER","duration":"2 hr 30 min"},"IM2007":{"date":"27 April 2021","day":"Tuesday","time":"9.00 am","code":"IM2007","name":"ENGINEERING MATHEMATICS II","duration":"2 hr 30 min"},"IM4490":{"date":"27 April 2021","day":"Tuesday","time":"9.00 am","code":"IM4490","name":"MULTIMEDIA SYSTEMS","duration":"2 hr"},"MA1001":{"date":"27 April 2021","day":"Tuesday","time":"9.00 am","code":"MA1001","name":"DYNAMICS","duration":"2 hr 30 min"},"MH4500":{"date":"27 April 2021","day":"Tuesday","time":"9.00 am","code":"MH4500","name":"TIME SERIES ANALYSIS","duration":"2 hr"},"BF2206":{"date":"27 April 2021","day":"Tuesday","time":"1.00 pm","code":"BF2206","name":"WEALTH MANAGEMENT","duration":"2 hr"},"BG4309":{"date":"27 April 2021","day":"Tuesday","time":"1.00 pm","code":"BG4309","name":"DRUG DELIVERY & TISSUE ENGINEERING","duration":"2 hr"},"BS3025":{"date":"27 April 2021","day":"Tuesday","time":"1.00 pm","code":"BS3025","name":"NUCLEAR MAGNETIC RESONANCE IN STRUCTURAL BIOLOGY","duration":"3 hr"},"CE3005":{"date":"27 April 2021","day":"Tuesday","time":"1.00 pm","code":"CE3005","name":"COMPUTER NETWORKS","duration":"2 hr"},"CH9202":{"date":"27 April 2021","day":"Tuesday","time":"1.00 pm","code":"CH9202","name":"FOOD PHYSICS","duration":"3 hr"},"CY1602":{"date":"27 April 2021","day":"Tuesday","time":"1.00 pm","code":"CY1602","name":"MATHEMATICS II","duration":"2 hr 30 min"},"CZ3006":{"date":"27 April 2021","day":"Tuesday","time":"1.00 pm","code":"CZ3006","name":"NET CENTRIC COMPUTING","duration":"2 hr"},"EE2002":{"date":"27 April 2021","day":"Tuesday","time":"1.00 pm","code":"EE2002","name":"ANALOG ELECTRONICS","duration":"2 hr 30 min"},"HE2015":{"date":"27 April 2021","day":"Tuesday","time":"1.00 pm","code":"HE2015","name":"MACROECONOMIC ISSUES & POLICIES IN CONTEMPORARY CHINA","duration":"2 hr 30 min"},"HE4004":{"date":"27 April 2021","day":"Tuesday","time":"1.00 pm","code":"HE4004","name":"BEHAVIORAL ECONOMICS","duration":"1 hr 30 min"},"HL2006":{"date":"27 April 2021","day":"Tuesday","time":"1.00 pm","code":"HL2006","name":"MODERNISM","duration":"2 hr 30 min"},"MA2005":{"date":"27 April 2021","day":"Tuesday","time":"1.00 pm","code":"MA2005","name":"ENGINEERING GRAPHICS","duration":"2 hr 30 min"},"MH1803":{"date":"27 April 2021","day":"Tuesday","time":"1.00 pm","code":"MH1803","name":"CALCULUS FOR PHYSICS","duration":"2 hr"},"MH1804":{"date":"27 April 2021","day":"Tuesday","time":"1.00 pm","code":"MH1804","name":"MATHEMATICS FOR CHEMISTRY","duration":"2 hr"},"MS2012":{"date":"27 April 2021","day":"Tuesday","time":"1.00 pm","code":"MS2012","name":"INTRODUCTION TO MANUFACTURING PROCESSES","duration":"2 hr"},"MS4612":{"date":"27 April 2021","day":"Tuesday","time":"1.00 pm","code":"MS4612","name":"DRUG DELIVERY & TISSUE ENGINEERING","duration":"2 hr"},"RE1012":{"date":"27 April 2021","day":"Tuesday","time":"1.00 pm","code":"RE1012","name":"MATHEMATICS II","duration":"2 hr 30 min"},"BR2206":{"date":"27 April 2021","day":"Tuesday","time":"5.00 pm","code":"BR2206","name":"LIFE INSURANCE UNDERWRITING & CLAIMS","duration":"2 hr 30 min"},"BS8001":{"date":"27 April 2021","day":"Tuesday","time":"5.00 pm","code":"BS8001","name":"HUMAN BODY FUNCTION & DISEASE","duration":"2 hr"},"CB2102":{"date":"27 April 2021","day":"Tuesday","time":"5.00 pm","code":"CB2102","name":"ORGANIC CHEMISTRY FOR ENGINEERS","duration":"2 hr 30 min"},"CE4041":{"date":"27 April 2021","day":"Tuesday","time":"5.00 pm","code":"CE4041","name":"MACHINE LEARNING","duration":"2 hr"},"CH2102":{"date":"27 April 2021","day":"Tuesday","time":"5.00 pm","code":"CH2102","name":"ORGANIC CHEMISTRY & SPECTROPHOTOMETRY","duration":"2 hr 30 min"},"CM9091":{"date":"27 April 2021","day":"Tuesday","time":"5.00 pm","code":"CM9091","name":"INDUSTRIAL & ENVIRONMENTAL CHEMISTRY","duration":"2 hr"},"CZ4041":{"date":"27 April 2021","day":"Tuesday","time":"5.00 pm","code":"CZ4041","name":"MACHINE LEARNING","duration":"2 hr"},"EE8092":{"date":"27 April 2021","day":"Tuesday","time":"5.00 pm","code":"EE8092","name":"DIGITAL LIFESTYLE","duration":"2 hr"},"HE2011":{"date":"27 April 2021","day":"Tuesday","time":"5.00 pm","code":"HE2011","name":"LABOUR ECONOMICS & LABOUR RELATIONS","duration":"2 hr 30 min"},"HE4010":{"date":"27 April 2021","day":"Tuesday","time":"5.00 pm","code":"HE4010","name":"SINGAPORE ECONOMY IN A GLOBALIZED WORLD","duration":"2 hr 30 min"},"HL0201":{"date":"27 April 2021","day":"Tuesday","time":"5.00 pm","code":"HL0201","name":"IMAGES OF SINGAPORE: LITERATURE, FILM & CULTURE","duration":"2 hr"},"HP2100":{"date":"27 April 2021","day":"Tuesday","time":"5.00 pm","code":"HP2100","name":"RESEARCH DESIGN & DATA ANALYSIS IN PSYCHOLOGY","duration":"2 hr 30 min"},"HT9301":{"date":"27 April 2021","day":"Tuesday","time":"5.00 pm","code":"HT9301","name":"LINGUISTICS, CULTURE & TRANSLATION","duration":"2 hr 30 min"},"HY8002":{"date":"27 April 2021","day":"Tuesday","time":"5.00 pm","code":"HY8002","name":"LOGIC & CRITICAL THINKING","duration":"2 hr"},"MA4843":{"date":"27 April 2021","day":"Tuesday","time":"5.00 pm","code":"MA4843","name":"MANAGEMENT OF PRODUCT DEVELOPMENT","duration":"2 hr 30 min"},"MA4845":{"date":"27 April 2021","day":"Tuesday","time":"5.00 pm","code":"MA4845","name":"MANUFACTURING AUTOMATION","duration":"2 hr"},"MT3006":{"date":"27 April 2021","day":"Tuesday","time":"5.00 pm","code":"MT3006","name":"SHIP CHARTERING","duration":"2 hr 30 min"},"AB1301":{"date":"28 April 2021","day":"Wednesday","time":"9.00 am","code":"AB1301","name":"BUSINESS LAW","duration":"2 hr 30 min"},"BS1007":{"date":"28 April 2021","day":"Wednesday","time":"9.00 am","code":"BS1007","name":"MOLECULAR & CELL BIOLOGY I","duration":"2 hr"},"CE2005":{"date":"28 April 2021","day":"Wednesday","time":"9.00 am","code":"CE2005","name":"OPERATING SYSTEMS","duration":"2 hr"},"CM2021":{"date":"28 April 2021","day":"Wednesday","time":"9.00 am","code":"CM2021","name":"INORGANIC & BIOINORGANIC CHEMISTRY","duration":"2 hr"},"CV2011":{"date":"28 April 2021","day":"Wednesday","time":"9.00 am","code":"CV2011","name":"STRUCTURAL ANALYSIS I","duration":"2 hr 30 min"},"CZ2005":{"date":"28 April 2021","day":"Wednesday","time":"9.00 am","code":"CZ2005","name":"OPERATING SYSTEMS","duration":"2 hr"},"EE3002":{"date":"28 April 2021","day":"Wednesday","time":"9.00 am","code":"EE3002","name":"MICROPROCESSORS","duration":"2 hr 30 min"},"HA1011":{"date":"28 April 2021","day":"Wednesday","time":"9.00 am","code":"HA1011","name":"POLITICS OF SINGAPORE","duration":"2 hr 30 min"},"HC3002":{"date":"28 April 2021","day":"Wednesday","time":"9.00 am","code":"HC3002","name":"HISTORY OF CHINESE THOUGHT","duration":"2 hr 30 min"},"HE9092":{"date":"28 April 2021","day":"Wednesday","time":"9.00 am","code":"HE9092","name":"ECONOMIC THEORY","duration":"2 hr 30 min"},"HS2004":{"date":"28 April 2021","day":"Wednesday","time":"9.00 am","code":"HS2004","name":"CULTURE, SELF & IDENTITY","duration":"2 hr"},"IM2002":{"date":"28 April 2021","day":"Wednesday","time":"9.00 am","code":"IM2002","name":"MICROPROCESSORS","duration":"2 hr 30 min"},"MA1701":{"date":"28 April 2021","day":"Wednesday","time":"9.00 am","code":"MA1701","name":"INTRODUCTION TO AEROSPACE ENGINEERING","duration":"2 hr 30 min"},"MH1101":{"date":"28 April 2021","day":"Wednesday","time":"9.00 am","code":"MH1101","name":"CALCULUS II","duration":"2 hr"},"MH3701":{"date":"28 April 2021","day":"Wednesday","time":"9.00 am","code":"MH3701","name":"BASIC OPTIMIZATION","duration":"2 hr"},"MS4661":{"date":"28 April 2021","day":"Wednesday","time":"9.00 am","code":"MS4661","name":"APPLICATN OF PATENTS & REGISTERED DESIGN IN ENG RELATED IND","duration":"2 hr"},"AC2301":{"date":"28 April 2021","day":"Wednesday","time":"1.00 pm","code":"AC2301","name":"PRINCIPLES OF TAXATION","duration":"2 hr 30 min"},"BE3201":{"date":"28 April 2021","day":"Wednesday","time":"1.00 pm","code":"BE3201","name":"ENTREPRENEURIAL FINANCE","duration":"2 hr"},"BG2110":{"date":"28 April 2021","day":"Wednesday","time":"1.00 pm","code":"BG2110","name":"BIOELECTRICITY","duration":"2 hr 30 min"},"BS2010":{"date":"28 April 2021","day":"Wednesday","time":"1.00 pm","code":"BS2010","name":"BIOIMAGING","duration":"2 hr"},"CE1104":{"date":"28 April 2021","day":"Wednesday","time":"1.00 pm","code":"CE1104","name":"LINEAR ALGEBRA FOR COMPUTING","duration":"2 hr"},"CV4113":{"date":"28 April 2021","day":"Wednesday","time":"1.00 pm","code":"CV4113","name":"HIGHWAY ENGINEERING","duration":"2 hr 30 min"},"CZ1104":{"date":"28 April 2021","day":"Wednesday","time":"1.00 pm","code":"CZ1104","name":"LINEAR ALGEBRA FOR COMPUTING","duration":"2 hr"},"EE2006":{"date":"28 April 2021","day":"Wednesday","time":"1.00 pm","code":"EE2006","name":"ENGINEERING MATHEMATICS I","duration":"2 hr 30 min"},"EE4455":{"date":"28 April 2021","day":"Wednesday","time":"1.00 pm","code":"EE4455","name":"EMBEDDED SYSTEMS","duration":"2 hr"},"EE4533":{"date":"28 April 2021","day":"Wednesday","time":"1.00 pm","code":"EE4533","name":"POWER APPARATUS & SYSTEM PROTECTION","duration":"2 hr"},"HC2014":{"date":"28 April 2021","day":"Wednesday","time":"1.00 pm","code":"HC2014","name":"CHINESE THEATRE & PERFORMANCE","duration":"2 hr 30 min"},"HE3014":{"date":"28 April 2021","day":"Wednesday","time":"1.00 pm","code":"HE3014","name":"ECONOMICS OF CORPORATE FINANCE","duration":"2 hr 30 min"},"HL3007":{"date":"28 April 2021","day":"Wednesday","time":"1.00 pm","code":"HL3007","name":"POSTCOLONIAL LITERATURE","duration":"2 hr 30 min"},"HP4103":{"date":"28 April 2021","day":"Wednesday","time":"1.00 pm","code":"HP4103","name":"THE FORENSIC PSYCHOLOGY OF CRIME, TERRORISM & DISASTERS","duration":"2 hr 30 min"},"IM2006":{"date":"28 April 2021","day":"Wednesday","time":"1.00 pm","code":"IM2006","name":"ENGINEERING MATHEMATICS I","duration":"2 hr 30 min"},"IM4455":{"date":"28 April 2021","day":"Wednesday","time":"1.00 pm","code":"IM4455","name":"EMBEDDED SYSTEMS","duration":"2 hr"},"MA2012":{"date":"28 April 2021","day":"Wednesday","time":"1.00 pm","code":"MA2012","name":"INTRODUCTION TO MECHATRONICS SYSTEMS DESIGN","duration":"2 hr"},"MA2700":{"date":"28 April 2021","day":"Wednesday","time":"1.00 pm","code":"MA2700","name":"AEROSPACE MATERIALS & MANUFACTURING PROCESSES","duration":"2 hr 30 min"},"MA3006":{"date":"28 April 2021","day":"Wednesday","time":"1.00 pm","code":"MA3006","name":"FLUID MECHANICS","duration":"2 hr 30 min"},"MH4310":{"date":"28 April 2021","day":"Wednesday","time":"1.00 pm","code":"MH4310","name":"CODING THEORY","duration":"2 hr"},"MS2016":{"date":"28 April 2021","day":"Wednesday","time":"1.00 pm","code":"MS2016","name":"PHASE TRANSFORMATION & KINETICS","duration":"2 hr"},"PH2102":{"date":"28 April 2021","day":"Wednesday","time":"1.00 pm","code":"PH2102","name":"ELECTROMAGNETISM","duration":"2 hr 30 min"},"BF3207":{"date":"28 April 2021","day":"Wednesday","time":"5.00 pm","code":"BF3207","name":"ALTERNATIVE INVESTMENTS","duration":"2 hr"},"CE4046":{"date":"28 April 2021","day":"Wednesday","time":"5.00 pm","code":"CE4046","name":"INTELLIGENT AGENTS","duration":"2 hr"},"CH3141":{"date":"28 April 2021","day":"Wednesday","time":"5.00 pm","code":"CH3141","name":"ADVANCED UNIT OPERATIONS","duration":"2 hr 30 min"},"CM8003":{"date":"28 April 2021","day":"Wednesday","time":"5.00 pm","code":"CM8003","name":"FROM ALCHEMY TO CHEMISTRY","duration":"2 hr"},"CM9102":{"date":"28 April 2021","day":"Wednesday","time":"5.00 pm","code":"CM9102","name":"FOOD ANALYSIS & SAFETY","duration":"2 hr"},"CZ4046":{"date":"28 April 2021","day":"Wednesday","time":"5.00 pm","code":"CZ4046","name":"INTELLIGENT AGENTS","duration":"2 hr"},"EE8087":{"date":"28 April 2021","day":"Wednesday","time":"5.00 pm","code":"EE8087","name":"LIVING WITH MATHEMATICS","duration":"2 hr"},"EM9107":{"date":"28 April 2021","day":"Wednesday","time":"5.00 pm","code":"EM9107","name":"ENVIRONMENTAL HEALTH & SAFETY MANAGEMENT","duration":"2 hr 30 min"},"HL8025":{"date":"28 April 2021","day":"Wednesday","time":"5.00 pm","code":"HL8025","name":"UTOPIAN & DYSTOPIAN FILM & LITERATURE","duration":"2 hr"},"HP2300":{"date":"28 April 2021","day":"Wednesday","time":"5.00 pm","code":"HP2300","name":"DEVELOPMENTAL PSYCHOLOGY","duration":"2 hr 30 min"},"HQ8010":{"date":"28 April 2021","day":"Wednesday","time":"5.00 pm","code":"HQ8010","name":"INTRODUCTION TO GENDER & DIVERSITY","duration":"2 hr"},"MA4829":{"date":"28 April 2021","day":"Wednesday","time":"5.00 pm","code":"MA4829","name":"MACHINE INTELLIGENCE","duration":"2 hr"},"MH8300":{"date":"28 April 2021","day":"Wednesday","time":"5.00 pm","code":"MH8300","name":"IT'S DISCREETLY DISCRETE WLD:MATHS IN REAL-LIFE APPLICATIONS","duration":"2 hr"},"PH1011":{"date":"28 April 2021","day":"Wednesday","time":"5.00 pm","code":"PH1011","name":"PHYSICS","duration":"2 hr 30 min"},"PH1012":{"date":"28 April 2021","day":"Wednesday","time":"5.00 pm","code":"PH1012","name":"PHYSICS A","duration":"2 hr 30 min"},"AB1201":{"date":"29 April 2021","day":"Thursday","time":"9.00 am","code":"AB1201","name":"FINANCIAL MANAGEMENT","duration":"2 hr"},"BA3205":{"date":"29 April 2021","day":"Thursday","time":"9.00 am","code":"BA3205","name":"ACTUARIAL COMPUTING","duration":"3 hr"},"BG4214":{"date":"29 April 2021","day":"Thursday","time":"9.00 am","code":"BG4214","name":"BIOMEDICAL OPTICS","duration":"2 hr"},"BS3028":{"date":"29 April 2021","day":"Thursday","time":"9.00 am","code":"BS3028","name":"NATURAL PRODUCTS IN MEDICINAL CHEMISTRY","duration":"2 hr 30 min"},"CE4015":{"date":"29 April 2021","day":"Thursday","time":"9.00 am","code":"CE4015","name":"SIMULATION & MODELLING","duration":"2 hr"},"CH1104":{"date":"29 April 2021","day":"Thursday","time":"9.00 am","code":"CH1104","name":"MATERIALS & ENERGY BALANCES","duration":"2 hr 30 min"},"CM2062":{"date":"29 April 2021","day":"Thursday","time":"9.00 am","code":"CM2062","name":"CHEMISTRY & BIOLOGICAL CHEMISTRY LABORATORY 2","duration":"2 hr"},"CZ2003":{"date":"29 April 2021","day":"Thursday","time":"9.00 am","code":"CZ2003","name":"COMPUTER GRAPHICS & VISUALISATION","duration":"2 hr"},"CZ4015":{"date":"29 April 2021","day":"Thursday","time":"9.00 am","code":"CZ4015","name":"SIMULATION & MODELLING","duration":"2 hr"},"EE2004":{"date":"29 April 2021","day":"Thursday","time":"9.00 am","code":"EE2004","name":"DIGITAL ELECTRONICS","duration":"2 hr 30 min"},"EN3004":{"date":"29 April 2021","day":"Thursday","time":"9.00 am","code":"EN3004","name":"AIR POLLUTION CONTROL ENGINEERING","duration":"2 hr 30 min"},"HA2011":{"date":"29 April 2021","day":"Thursday","time":"9.00 am","code":"HA2011","name":"COST-BENEFIT ANALYSIS IN PUBLIC POLICY","duration":"2 hr 30 min"},"HC1051":{"date":"29 April 2021","day":"Thursday","time":"9.00 am","code":"HC1051","name":"MODERN CHINESE","duration":"2 hr 30 min"},"HE3022":{"date":"29 April 2021","day":"Thursday","time":"9.00 am","code":"HE3022","name":"ECONOMETRIC MODELLING & FORECASTING","duration":"2 hr 30 min"},"HP4105":{"date":"29 April 2021","day":"Thursday","time":"9.00 am","code":"HP4105","name":"CORRECTIONAL PSYCHOLOGY","duration":"2 hr 30 min"},"HS2023":{"date":"29 April 2021","day":"Thursday","time":"9.00 am","code":"HS2023","name":"ENVIRONMENTAL SOCIOLOGY","duration":"2 hr 30 min"},"IM1004":{"date":"29 April 2021","day":"Thursday","time":"9.00 am","code":"IM1004","name":"DIGITAL ELECTRONICS","duration":"2 hr 30 min"},"MA8103":{"date":"29 April 2021","day":"Thursday","time":"9.00 am","code":"MA8103","name":"HUMAN RESOURCE MANAGEMENT","duration":"2 hr"},"MH3400":{"date":"29 April 2021","day":"Thursday","time":"9.00 am","code":"MH3400","name":"ALGORITHMS FOR THE REAL WORLD","duration":"2 hr"},"MS4012":{"date":"29 April 2021","day":"Thursday","time":"9.00 am","code":"MS4012","name":"QUALITY CONTROL","duration":"2 hr"},"MT4103":{"date":"29 April 2021","day":"Thursday","time":"9.00 am","code":"MT4103","name":"PORT PLANNING & OPERATIONS","duration":"2 hr 30 min"},"PH4404":{"date":"29 April 2021","day":"Thursday","time":"9.00 am","code":"PH4404","name":"NANOSCALE PHYSICS","duration":"2 hr 30 min"},"AC2302":{"date":"29 April 2021","day":"Thursday","time":"1.00 pm","code":"AC2302","name":"COMPANY LAW & CORPORATE GOVERNANCE","duration":"2 hr 30 min"},"CE1106":{"date":"29 April 2021","day":"Thursday","time":"1.00 pm","code":"CE1106","name":"COMPUTER ORGANISATION & ARCHITECTURE","duration":"2 hr"},"CH9200":{"date":"29 April 2021","day":"Thursday","time":"1.00 pm","code":"CH9200","name":"FOOD MICROBIOLOGY","duration":"3 hr"},"CM4011":{"date":"29 April 2021","day":"Thursday","time":"1.00 pm","code":"CM4011","name":"ADVANCED ANALYTICAL CHEMISTRY","duration":"2 hr"},"CV4119":{"date":"29 April 2021","day":"Thursday","time":"1.00 pm","code":"CV4119","name":"ADVANCED PREFABRICATION & PRECAST CONSTRUCTION","duration":"2 hr 30 min"},"CZ1106":{"date":"29 April 2021","day":"Thursday","time":"1.00 pm","code":"CZ1106","name":"COMPUTER ORGANISATION & ARCHITECTURE","duration":"2 hr"},"EE2008":{"date":"29 April 2021","day":"Thursday","time":"1.00 pm","code":"EE2008","name":"DATA STRUCTURES & ALGORITHMS","duration":"2 hr 30 min"},"EE4343":{"date":"29 April 2021","day":"Thursday","time":"1.00 pm","code":"EE4343","name":"RADIO FREQUENCY CIRCUITS","duration":"2 hr"},"EE4504":{"date":"29 April 2021","day":"Thursday","time":"1.00 pm","code":"EE4504","name":"DESIGN OF CLEAN ENERGY SYSTEMS","duration":"2 hr"},"HC2031":{"date":"29 April 2021","day":"Thursday","time":"1.00 pm","code":"HC2031","name":"CONFUCIAN THOUGHT","duration":"2 hr 30 min"},"HE4011":{"date":"29 April 2021","day":"Thursday","time":"1.00 pm","code":"HE4011","name":"CURRENT TOPICS IN ECONOMICS","duration":"2 hr 30 min"},"HL3012":{"date":"29 April 2021","day":"Thursday","time":"1.00 pm","code":"HL3012","name":"THE DISCOURSE OF LOVE","duration":"2 hr 30 min"},"HP4102":{"date":"29 April 2021","day":"Thursday","time":"1.00 pm","code":"HP4102","name":"TRAUMA PSYCHOLOGY & CRISIS MANAGEMENT","duration":"2 hr 30 min"},"IM1001":{"date":"29 April 2021","day":"Thursday","time":"1.00 pm","code":"IM1001","name":"DATA STRUCTURES & ALGORITHMS","duration":"2 hr 30 min"},"MA2001":{"date":"29 April 2021","day":"Thursday","time":"1.00 pm","code":"MA2001","name":"MECHANICS OF MATERIALS","duration":"2 hr 30 min"},"MH4501":{"date":"29 April 2021","day":"Thursday","time":"1.00 pm","code":"MH4501","name":"MULTIVARIATE ANALYSIS","duration":"2 hr"},"MS1015":{"date":"29 April 2021","day":"Thursday","time":"1.00 pm","code":"MS1015","name":"MATERIALS SCIENCE","duration":"2 hr"},"PH1106":{"date":"29 April 2021","day":"Thursday","time":"1.00 pm","code":"PH1106","name":"ELECTRICITY & MAGNETISM","duration":"2 hr 30 min"},"BU8201":{"date":"29 April 2021","day":"Thursday","time":"5.00 pm","code":"BU8201","name":"BUSINESS FINANCE","duration":"2 hr"},"BU8241":{"date":"29 April 2021","day":"Thursday","time":"5.00 pm","code":"BU8241","name":"FINANCIAL WELLBEING","duration":"2 hr"},"CE4024":{"date":"29 April 2021","day":"Thursday","time":"5.00 pm","code":"CE4024","name":"CRYPTOGRAPHY & NETWORK SECURITY","duration":"2 hr"},"CH9220":{"date":"29 April 2021","day":"Thursday","time":"5.00 pm","code":"CH9220","name":"FOOD STANDARDS - IN FOOD PRODUCTION & TRADE","duration":"2 hr"},"CM9031":{"date":"29 April 2021","day":"Thursday","time":"5.00 pm","code":"CM9031","name":"ANALYTICAL & MANUFACTURING TECHNIQUES IN PHARMA INDUSTRY","duration":"2 hr"},"CV1012":{"date":"29 April 2021","day":"Thursday","time":"5.00 pm","code":"CV1012","name":"FLUID MECHANICS","duration":"2 hr 30 min"},"CZ4024":{"date":"29 April 2021","day":"Thursday","time":"5.00 pm","code":"CZ4024","name":"CRYPTOGRAPHY & NETWORK SECURITY","duration":"2 hr"},"ES8007":{"date":"29 April 2021","day":"Thursday","time":"5.00 pm","code":"ES8007","name":"CLIMATE & CLIMATE CHANGE","duration":"2 hr"},"HC4042":{"date":"29 April 2021","day":"Thursday","time":"5.00 pm","code":"HC4042","name":"CHINA & GLOBALISATION","duration":"2 hr 30 min"},"HE9091":{"date":"29 April 2021","day":"Thursday","time":"5.00 pm","code":"HE9091","name":"PRINCIPLES OF ECONOMICS","duration":"2 hr 30 min"},"HL8001":{"date":"29 April 2021","day":"Thursday","time":"5.00 pm","code":"HL8001","name":"MADNESS IN LITERATURE & FILM","duration":"2 hr"},"HP3204":{"date":"29 April 2021","day":"Thursday","time":"5.00 pm","code":"HP3204","name":"AN APE'S GUIDE TO HUMAN LANGUAGE","duration":"2 hr 30 min"},"MA4853":{"date":"29 April 2021","day":"Thursday","time":"5.00 pm","code":"MA4853","name":"MANUFACTURING SYSTEMS","duration":"2 hr 30 min"},"BF3201":{"date":"30 April 2021","day":"Friday","time":"9.00 am","code":"BF3201","name":"CORPORATE FINANCE & STRATEGY","duration":"2 hr"},"BR3203":{"date":"30 April 2021","day":"Friday","time":"9.00 am","code":"BR3203","name":"PRINCIPLES OF ENTERPRISE RISK MANAGEMENT","duration":"2 hr 30 min"},"BS2021":{"date":"30 April 2021","day":"Friday","time":"9.00 am","code":"BS2021","name":"RNA STRUCTURES & RNA BASED DRUG DEVELOPMENT","duration":"2 hr 30 min"},"CE4013":{"date":"30 April 2021","day":"Friday","time":"9.00 am","code":"CE4013","name":"DISTRIBUTED SYSTEMS","duration":"2 hr"},"CH3104":{"date":"30 April 2021","day":"Friday","time":"9.00 am","code":"CH3104","name":"BIOCHEMICAL ENGINEERING","duration":"2 hr 30 min"},"CM4042":{"date":"30 April 2021","day":"Friday","time":"9.00 am","code":"CM4042","name":"CHEMICAL KINETICS & DYNAMICS","duration":"2 hr"},"CV4107":{"date":"30 April 2021","day":"Friday","time":"9.00 am","code":"CV4107","name":"ENGINEERING ECONOMICS & FINANCE","duration":"2 hr 30 min"},"CZ2004":{"date":"30 April 2021","day":"Friday","time":"9.00 am","code":"CZ2004","name":"HUMAN COMPUTER INTERACTION","duration":"2 hr"},"CZ4013":{"date":"30 April 2021","day":"Friday","time":"9.00 am","code":"CZ4013","name":"DISTRIBUTED SYSTEMS","duration":"2 hr"},"EE3015":{"date":"30 April 2021","day":"Friday","time":"9.00 am","code":"EE3015","name":"POWER SYSTEMS & CONVERSION","duration":"2 hr"},"EE4153":{"date":"30 April 2021","day":"Friday","time":"9.00 am","code":"EE4153","name":"TELECOMMUNICATION SYSTEMS","duration":"2 hr"},"EE4208":{"date":"30 April 2021","day":"Friday","time":"9.00 am","code":"EE4208","name":"INTELLIGENT SYSTEMS DESIGN","duration":"2 hr"},"HA2024":{"date":"30 April 2021","day":"Friday","time":"9.00 am","code":"HA2024","name":"STATISTICAL FOUNDATIONS FOR PUBLIC ADMNISTRATION & POLICY","duration":"2 hr 30 min"},"HE3005":{"date":"30 April 2021","day":"Friday","time":"9.00 am","code":"HE3005","name":"ENVIRONMENTAL ECONOMICS","duration":"2 hr 30 min"},"HH1004":{"date":"30 April 2021","day":"Friday","time":"9.00 am","code":"HH1004","name":"SCIENCE & TECHNOLOGY IN HISTORICAL PERSPECTIVE","duration":"2 hr 30 min"},"HL1006":{"date":"30 April 2021","day":"Friday","time":"9.00 am","code":"HL1006","name":"INTRODUCTION TO AMERICAN LITERATURE","duration":"2 hr 30 min"},"HP1000":{"date":"30 April 2021","day":"Friday","time":"9.00 am","code":"HP1000","name":"INTRODUCTION TO PSYCHOLOGY","duration":"2 hr 30 min"},"HP3206":{"date":"30 April 2021","day":"Friday","time":"9.00 am","code":"HP3206","name":"ENVIRONMENTAL PSYCHOLOGY","duration":"2 hr 30 min"},"HS2029":{"date":"30 April 2021","day":"Friday","time":"9.00 am","code":"HS2029","name":"SOCIAL POLICY & SOCIAL CHANGE","duration":"2 hr 30 min"},"IM4153":{"date":"30 April 2021","day":"Friday","time":"9.00 am","code":"IM4153","name":"TELECOMMUNICATION SYSTEMS","duration":"2 hr"},"MA3003":{"date":"30 April 2021","day":"Friday","time":"9.00 am","code":"MA3003","name":"HEAT TRANSFER","duration":"2 hr 30 min"},"MS4630":{"date":"30 April 2021","day":"Friday","time":"9.00 am","code":"MS4630","name":"PHOTOVOLTAIC DEVICES & ENERGY STORAGE","duration":"2 hr"},"MT4003":{"date":"30 April 2021","day":"Friday","time":"9.00 am","code":"MT4003","name":"MARITIME STRATEGY","duration":"2 hr 30 min"},"RE1016":{"date":"30 April 2021","day":"Friday","time":"9.00 am","code":"RE1016","name":"ENGINEERING COMPUTATION","duration":"2 hr"},"BF2210":{"date":"30 April 2021","day":"Friday","time":"2.30 pm","code":"BF2210","name":"RISK MANAGEMENT OF FINANCIAL INSTITUTIONS","duration":"2 hr 30 min"},"BF2216":{"date":"30 April 2021","day":"Friday","time":"2.30 pm","code":"BF2216","name":"TRADE INCOTERMS & SHIP CHARTERING","duration":"2 hr 30 min"},"BH3301":{"date":"30 April 2021","day":"Friday","time":"2.30 pm","code":"BH3301","name":"EMPLOYMENT LAW","duration":"2 hr 30 min"},"BS4018":{"date":"30 April 2021","day":"Friday","time":"2.30 pm","code":"BS4018","name":"BIOLOGY OF AGING & NEURODEGENERATION","duration":"2 hr 30 min"},"CB1131":{"date":"30 April 2021","day":"Friday","time":"2.30 pm","code":"CB1131","name":"INTRODUCTION TO BIOMOLECULAR ENGINEERING","duration":"2 hr 30 min"},"CV3012":{"date":"30 April 2021","day":"Friday","time":"2.30 pm","code":"CV3012","name":"STEEL DESIGN","duration":"2 hr 30 min"},"CZ3003":{"date":"30 April 2021","day":"Friday","time":"2.30 pm","code":"CZ3003","name":"SOFTWARE SYSTEMS ANALYSIS & DESIGN","duration":"2 hr"},"EE3001":{"date":"30 April 2021","day":"Friday","time":"2.30 pm","code":"EE3001","name":"ENGINEERING ELECTROMAGNETICS","duration":"2 hr 30 min"},"EE4718":{"date":"30 April 2021","day":"Friday","time":"2.30 pm","code":"EE4718","name":"ENTERPRISE NETWORK DESIGN","duration":"2 hr"},"HC3001":{"date":"30 April 2021","day":"Friday","time":"2.30 pm","code":"HC3001","name":"MODERN CHINESE LITERATURE","duration":"2 hr 30 min"},"HE3023":{"date":"30 April 2021","day":"Friday","time":"2.30 pm","code":"HE3023","name":"ECONOMETRIC ANALYSIS OF FINANCIAL DATA","duration":"2 hr 30 min"},"HL2021":{"date":"30 April 2021","day":"Friday","time":"2.30 pm","code":"HL2021","name":"LITERATURE OF EMPIRE","duration":"2 hr 30 min"},"IM1002":{"date":"30 April 2021","day":"Friday","time":"2.30 pm","code":"IM1002","name":"ANALOG ELECTRONICS","duration":"2 hr"},"IM4718":{"date":"30 April 2021","day":"Friday","time":"2.30 pm","code":"IM4718","name":"ENTERPRISE NETWORK DESIGN","duration":"2 hr"},"MA1002":{"date":"30 April 2021","day":"Friday","time":"2.30 pm","code":"MA1002","name":"FUNDAMENTAL ENGINEERING MATERIALS","duration":"2 hr"},"MH4110":{"date":"30 April 2021","day":"Friday","time":"2.30 pm","code":"MH4110","name":"PARTIAL DIFFERENTIAL EQUATIONS","duration":"2 hr"},"MH4517":{"date":"30 April 2021","day":"Friday","time":"2.30 pm","code":"MH4517","name":"DATA APPLICATIONS IN NATURAL SCIENCES","duration":"2 hr"},"MS4662":{"date":"30 April 2021","day":"Friday","time":"2.30 pm","code":"MS4662","name":"APPRECIATING IP IN RESEARCH & DEVELOPMENT","duration":"2 hr"},"AC2101":{"date":"3 May 2021","day":"Monday","time":"9.00 am","code":"AC2101","name":"ACCOUNTING RECOGNITION & MEASUREMENT","duration":"2 hr 30 min"},"BS211S":{"date":"3 May 2021","day":"Monday","time":"9.00 am","code":"BS211S","name":"EQUATIONS OF LIFE","duration":"2 hr"},"CE2001":{"date":"3 May 2021","day":"Monday","time":"9.00 am","code":"CE2001","name":"ALGORITHMS","duration":"2 hr"},"CE4067":{"date":"3 May 2021","day":"Monday","time":"9.00 am","code":"CE4067","name":"SOFTWARE SECURITY","duration":"2 hr"},"CM3011":{"date":"3 May 2021","day":"Monday","time":"9.00 am","code":"CM3011","name":"CHEMICAL SPECTROSCOPY & APPLICATIONS","duration":"2 hr"},"CM9103":{"date":"3 May 2021","day":"Monday","time":"9.00 am","code":"CM9103","name":"FOOD PROCESSING & PRESERVATION","duration":"2 hr"},"CV1013":{"date":"3 May 2021","day":"Monday","time":"9.00 am","code":"CV1013","name":"CIVIL ENGINEERING MATERIALS","duration":"2 hr 30 min"},"CV4111":{"date":"3 May 2021","day":"Monday","time":"9.00 am","code":"CV4111","name":"GROUND ENGINEERING","duration":"2 hr 30 min"},"CZ2001":{"date":"3 May 2021","day":"Monday","time":"9.00 am","code":"CZ2001","name":"ALGORITHMS","duration":"2 hr"},"CZ4067":{"date":"3 May 2021","day":"Monday","time":"9.00 am","code":"CZ4067","name":"SOFTWARE SECURITY","duration":"2 hr"},"EE2001":{"date":"3 May 2021","day":"Monday","time":"9.00 am","code":"EE2001","name":"CIRCUIT ANALYSIS","duration":"2 hr 30 min"},"EE3010":{"date":"3 May 2021","day":"Monday","time":"9.00 am","code":"EE3010","name":"ELECTRICAL DEVICES & MACHINES","duration":"2 hr"},"EE3019":{"date":"3 May 2021","day":"Monday","time":"9.00 am","code":"EE3019","name":"INTEGRATED ELECTRONICS","duration":"2 hr"},"EE4001":{"date":"3 May 2021","day":"Monday","time":"9.00 am","code":"EE4001","name":"SOFTWARE ENGINEERING","duration":"2 hr"},"HA3010":{"date":"3 May 2021","day":"Monday","time":"9.00 am","code":"HA3010","name":"MASS MEDIA & PUBLIC POLICY","duration":"2 hr 30 min"},"HE2002":{"date":"3 May 2021","day":"Monday","time":"9.00 am","code":"HE2002","name":"INTERMEDIATE MACROECONOMICS","duration":"2 hr 30 min"},"HE3002":{"date":"3 May 2021","day":"Monday","time":"9.00 am","code":"HE3002","name":"GAME THEORY & APPLICATIONS TO SOCIAL SCIENCES","duration":"2 hr 30 min"},"HL2015":{"date":"3 May 2021","day":"Monday","time":"9.00 am","code":"HL2015","name":"WAR IN LITERATURE & FILM","duration":"2 hr 30 min"},"IM2001":{"date":"3 May 2021","day":"Monday","time":"9.00 am","code":"IM2001","name":"SOFTWARE ENGINEERING","duration":"2 hr"},"MA4001":{"date":"3 May 2021","day":"Monday","time":"9.00 am","code":"MA4001","name":"ENGINEERING DESIGN","duration":"2 hr 30 min"},"MA4012":{"date":"3 May 2021","day":"Monday","time":"9.00 am","code":"MA4012","name":"MECHATRONICS ENGINEERING DESIGN","duration":"2 hr 30 min"},"MH2802":{"date":"3 May 2021","day":"Monday","time":"9.00 am","code":"MH2802","name":"LINEAR ALGEBRA FOR SCIENTISTS","duration":"2 hr 30 min"},"MH4100":{"date":"3 May 2021","day":"Monday","time":"9.00 am","code":"MH4100","name":"REAL ANALYSIS II","duration":"2 hr"},"MS1012":{"date":"3 May 2021","day":"Monday","time":"9.00 am","code":"MS1012","name":"MATERIALS PHYSICS","duration":"2 hr"},"MS4611":{"date":"3 May 2021","day":"Monday","time":"9.00 am","code":"MS4611","name":"BIOMEDICAL DEVICES","duration":"2 hr"},"MT0001":{"date":"3 May 2021","day":"Monday","time":"9.00 am","code":"MT0001","name":"SHIPPING & THE ENVIRONMENT","duration":"2 hr 30 min"},"AC3104":{"date":"3 May 2021","day":"Monday","time":"1.00 pm","code":"AC3104","name":"RISK MANAGEMENT & ADVANCED AUDITING","duration":"2 hr 30 min"},"BS2104":{"date":"3 May 2021","day":"Monday","time":"1.00 pm","code":"BS2104","name":"BIOMEDICAL PHARMACOLOGY","duration":"2 hr 30 min"},"CE1105":{"date":"3 May 2021","day":"Monday","time":"1.00 pm","code":"CE1105","name":"DIGITAL LOGIC","duration":"2 hr"},"CH9204":{"date":"3 May 2021","day":"Monday","time":"1.00 pm","code":"CH9204","name":"QUALITY SYSTEMS OPERATIONS","duration":"2 hr"},"CM1041":{"date":"3 May 2021","day":"Monday","time":"1.00 pm","code":"CM1041","name":"BASIC PHYSICAL CHEMISTRY WITH LABORATORY","duration":"2 hr"},"CZ1105":{"date":"3 May 2021","day":"Monday","time":"1.00 pm","code":"CZ1105","name":"DIGITAL LOGIC","duration":"2 hr"},"CZ3002":{"date":"3 May 2021","day":"Monday","time":"1.00 pm","code":"CZ3002","name":"ADVANCED SOFTWARE ENGINEERING","duration":"2 hr"},"EE4109":{"date":"3 May 2021","day":"Monday","time":"1.00 pm","code":"EE4109","name":"WIRELESS SYSTEM DESIGN","duration":"2 hr"},"EE4304":{"date":"3 May 2021","day":"Monday","time":"1.00 pm","code":"EE4304","name":"RADIO FREQUENCY INTEGRATED SYSTEM DESIGN","duration":"2 hr"},"EE4791":{"date":"3 May 2021","day":"Monday","time":"1.00 pm","code":"EE4791","name":"DATABASE SYSTEMS","duration":"2 hr"},"EN2003":{"date":"3 May 2021","day":"Monday","time":"1.00 pm","code":"EN2003","name":"WATER SUPPLY ENGINEERING","duration":"2 hr 30 min"},"HE4013":{"date":"3 May 2021","day":"Monday","time":"1.00 pm","code":"HE4013","name":"EXPERIMENTAL ECONOMICS","duration":"2 hr 30 min"},"HL2029":{"date":"3 May 2021","day":"Monday","time":"1.00 pm","code":"HL2029","name":"AMERICAN MODERNISM","duration":"2 hr 30 min"},"HL4034":{"date":"3 May 2021","day":"Monday","time":"1.00 pm","code":"HL4034","name":"BRITISH ASIAN LITERATURE","duration":"2 hr 30 min"},"HS3002":{"date":"3 May 2021","day":"Monday","time":"1.00 pm","code":"HS3002","name":"UNDERSTANDING SOCIAL STATISTICS","duration":"2 hr 30 min"},"IM4791":{"date":"3 May 2021","day":"Monday","time":"1.00 pm","code":"IM4791","name":"DATABASE SYSTEMS","duration":"2 hr"},"MA2009":{"date":"3 May 2021","day":"Monday","time":"1.00 pm","code":"MA2009","name":"INTRODUCTION TO ELECTRICAL CIRCUITS & ELECTRONIC DEVICES","duration":"2 hr 30 min"},"MA8005":{"date":"3 May 2021","day":"Monday","time":"1.00 pm","code":"MA8005","name":"AIRCRAFT ELECTRICAL & ELECTRONICS CIRCUITS","duration":"2 hr 30 min"},"MH3500":{"date":"3 May 2021","day":"Monday","time":"1.00 pm","code":"MH3500","name":"STATISTICS","duration":"2 hr"},"MS2014":{"date":"3 May 2021","day":"Monday","time":"1.00 pm","code":"MS2014","name":"MATERIALS STRUCTURE & DEFECTS","duration":"2 hr"},"PH3201":{"date":"3 May 2021","day":"Monday","time":"1.00 pm","code":"PH3201","name":"STATISTICAL MECHANICS I","duration":"2 hr 30 min"},"CB1105":{"date":"3 May 2021","day":"Monday","time":"5.00 pm","code":"CB1105","name":"MATERIALS SCIENCE","duration":"2 hr"},"CE9010":{"date":"3 May 2021","day":"Monday","time":"5.00 pm","code":"CE9010","name":"INTRODUCTION TO DATA ANALYSIS","duration":"2 hr"},"EE8093":{"date":"3 May 2021","day":"Monday","time":"5.00 pm","code":"EE8093","name":"ENERGY DEVICES FOR SUSTAINABLE URBAN ENVIRONMENT","duration":"2 hr"},"EN0002":{"date":"3 May 2021","day":"Monday","time":"5.00 pm","code":"EN0002","name":"ENVIRONMENTAL ISSUES & SUSTAINABILITY","duration":"2 hr 30 min"},"HC2040":{"date":"3 May 2021","day":"Monday","time":"5.00 pm","code":"HC2040","name":"UNDERSTANDING CHINA","duration":"2 hr 30 min"},"HL4030":{"date":"3 May 2021","day":"Monday","time":"5.00 pm","code":"HL4030","name":"SCOTTISH LITERATURE","duration":"2 hr 30 min"},"HP2700":{"date":"3 May 2021","day":"Monday","time":"5.00 pm","code":"HP2700","name":"ABNORMAL PSYCHOLOGY","duration":"2 hr 30 min"},"HP8003":{"date":"3 May 2021","day":"Monday","time":"5.00 pm","code":"HP8003","name":"ARE YOU OKAY? MENTAL HEALTH IN SINGAPORE","duration":"2 hr"},"MA4854":{"date":"3 May 2021","day":"Monday","time":"5.00 pm","code":"MA4854","name":"QUALITY ASSURANCE & MANAGEMENT","duration":"2 hr 30 min"},"MA4872":{"date":"3 May 2021","day":"Monday","time":"5.00 pm","code":"MA4872","name":"AIRCRAFT RELIABILITY & MAINTAINABILITY","duration":"2 hr 30 min"},"MT2004":{"date":"3 May 2021","day":"Monday","time":"5.00 pm","code":"MT2004","name":"MATHEMATICS II FOR MARITIME STUDIES","duration":"2 hr 30 min"},"MT4102":{"date":"3 May 2021","day":"Monday","time":"5.00 pm","code":"MT4102","name":"DISTRIBUTION & WAREHOUSING","duration":"2 hr 30 min"},"PH1802":{"date":"3 May 2021","day":"Monday","time":"5.00 pm","code":"PH1802","name":"FOUNDATIONS OF PHYSICS II","duration":"2 hr 30 min"},"PH4414":{"date":"3 May 2021","day":"Monday","time":"5.00 pm","code":"PH4414","name":"INTRODUCTION TO SPINTRONICS","duration":"2 hr 30 min"},"AC3102":{"date":"4 May 2021","day":"Tuesday","time":"9.00 am","code":"AC3102","name":"RISK REPORTING & ANALYSIS","duration":"2 hr 30 min"},"BF2201":{"date":"4 May 2021","day":"Tuesday","time":"9.00 am","code":"BF2201","name":"INVESTMENTS","duration":"2 hr"},"BG4313":{"date":"4 May 2021","day":"Tuesday","time":"9.00 am","code":"BG4313","name":"GLOBAL MEDICAL DEVICE REGULATORY OVERVIEW","duration":"2 hr"},"BS0005":{"date":"4 May 2021","day":"Tuesday","time":"9.00 am","code":"BS0005","name":"ONE HEALTH","duration":"2 hr 30 min"},"CE2101":{"date":"4 May 2021","day":"Tuesday","time":"9.00 am","code":"CE2101","name":"ALGORITHM DESIGN & ANALYSIS","duration":"2 hr"},"CM3061":{"date":"4 May 2021","day":"Tuesday","time":"9.00 am","code":"CM3061","name":"CHEMISTRY & BIOLOGICAL CHEMISTRY LABORATORY 3","duration":"2 hr"},"CV3016":{"date":"4 May 2021","day":"Tuesday","time":"9.00 am","code":"CV3016","name":"CONSTRUCTION TECHNOLOGY & PROCESSES","duration":"2 hr 30 min"},"CZ2007":{"date":"4 May 2021","day":"Tuesday","time":"9.00 am","code":"CZ2007","name":"INTRODUCTION TO DATABASES","duration":"2 hr"},"CZ2101":{"date":"4 May 2021","day":"Tuesday","time":"9.00 am","code":"CZ2101","name":"ALGORITHM DESIGN & ANALYSIS","duration":"2 hr"},"EE3011":{"date":"4 May 2021","day":"Tuesday","time":"9.00 am","code":"EE3011","name":"MODELLING & CONTROL","duration":"2 hr"},"EE4534":{"date":"4 May 2021","day":"Tuesday","time":"9.00 am","code":"EE4534","name":"MODERN DISTRIBUTION SYSTEMS WITH RENEWABLE RESOURCES","duration":"2 hr"},"EE4614":{"date":"4 May 2021","day":"Tuesday","time":"9.00 am","code":"EE4614","name":"DEVICE PARAMETER EXTRACTION & LAYOUT IMPLEMENTATION","duration":"2 hr"},"EE4756":{"date":"4 May 2021","day":"Tuesday","time":"9.00 am","code":"EE4756","name":"COMPUTER ARCHITECTURE","duration":"2 hr"},"HC2003":{"date":"4 May 2021","day":"Tuesday","time":"9.00 am","code":"HC2003","name":"LITERATURE OF TANG & SONG","duration":"2 hr 30 min"},"HL4018":{"date":"4 May 2021","day":"Tuesday","time":"9.00 am","code":"HL4018","name":"ADVANCED STUDIES IN ROMANTICISM","duration":"2 hr 30 min"},"HS3011":{"date":"4 May 2021","day":"Tuesday","time":"9.00 am","code":"HS3011","name":"POWER, POLITICS & THE STATE","duration":"2 hr 30 min"},"IM4756":{"date":"4 May 2021","day":"Tuesday","time":"9.00 am","code":"IM4756","name":"COMPUTER ARCHITECTURE","duration":"2 hr"},"MA2004":{"date":"4 May 2021","day":"Tuesday","time":"9.00 am","code":"MA2004","name":"MANUFACTURING PROCESSES","duration":"2 hr 30 min"},"MA3703":{"date":"4 May 2021","day":"Tuesday","time":"9.00 am","code":"MA3703","name":"FLIGHT DYNAMICS","duration":"2 hr"},"MA4846":{"date":"4 May 2021","day":"Tuesday","time":"9.00 am","code":"MA4846","name":"PRODUCT DESIGN ENGINEERING","duration":"2 hr 30 min"},"MH1810":{"date":"4 May 2021","day":"Tuesday","time":"9.00 am","code":"MH1810","name":"MATHEMATICS 1","duration":"2 hr"},"MS3012":{"date":"4 May 2021","day":"Tuesday","time":"9.00 am","code":"MS3012","name":"MICRO\/NANOELECTRONIC MATERIALS PROCESSING","duration":"2 hr"},"PH2601":{"date":"4 May 2021","day":"Tuesday","time":"9.00 am","code":"PH2601","name":"INTRODUCTION TO LASERS","duration":"2 hr"},"PH4605":{"date":"4 May 2021","day":"Tuesday","time":"9.00 am","code":"PH4605","name":"MEDICAL PHYSICS FOR RADIOTHERAPY","duration":"2 hr 30 min"},"AC2104":{"date":"4 May 2021","day":"Tuesday","time":"1.00 pm","code":"AC2104","name":"ASSURANCE & AUDITING","duration":"2 hr 30 min"},"CE3103":{"date":"4 May 2021","day":"Tuesday","time":"1.00 pm","code":"CE3103","name":"EMBEDDED PROGRAMMING","duration":"2 hr"},"CZ3007":{"date":"4 May 2021","day":"Tuesday","time":"1.00 pm","code":"CZ3007","name":"COMPILER TECHNIQUES","duration":"2 hr"},"EE1003":{"date":"4 May 2021","day":"Tuesday","time":"1.00 pm","code":"EE1003","name":"INTRODUCTION TO MATERIALS FOR ELECTRONICS","duration":"2 hr"},"EE3012":{"date":"4 May 2021","day":"Tuesday","time":"1.00 pm","code":"EE3012","name":"COMMUNICATION PRINCIPLES","duration":"2 hr"},"HC4035":{"date":"4 May 2021","day":"Tuesday","time":"1.00 pm","code":"HC4035","name":"WESTERN INFLUENCES ON MODERN CHINESE THOUGHT","duration":"2 hr 30 min"},"HE2001":{"date":"4 May 2021","day":"Tuesday","time":"1.00 pm","code":"HE2001","name":"INTERMEDIATE MICROECONOMICS","duration":"2 hr 30 min"},"HL2028":{"date":"4 May 2021","day":"Tuesday","time":"1.00 pm","code":"HL2028","name":"NINETEENTH CENTURY AMERICAN LITERATURE & CULTURE","duration":"2 hr 30 min"},"HP2600":{"date":"4 May 2021","day":"Tuesday","time":"1.00 pm","code":"HP2600","name":"COGNITIVE PSYCHOLOGY","duration":"2 hr 30 min"},"IM1003":{"date":"4 May 2021","day":"Tuesday","time":"1.00 pm","code":"IM1003","name":"OBJECT-ORIENTED PROGRAMMING","duration":"2 hr"},"IM3002":{"date":"4 May 2021","day":"Tuesday","time":"1.00 pm","code":"IM3002","name":"COMMUNICATION PRINCIPLES","duration":"2 hr"},"MA3005":{"date":"4 May 2021","day":"Tuesday","time":"1.00 pm","code":"MA3005","name":"CONTROL THEORY","duration":"2 hr 30 min"},"MA3705":{"date":"4 May 2021","day":"Tuesday","time":"1.00 pm","code":"MA3705","name":"AEROSPACE CONTROL THEORY","duration":"2 hr 30 min"},"MH2811":{"date":"4 May 2021","day":"Tuesday","time":"1.00 pm","code":"MH2811","name":"MATHEMATICS II","duration":"2 hr"},"MH4514":{"date":"4 May 2021","day":"Tuesday","time":"1.00 pm","code":"MH4514","name":"FINANCIAL MATHEMATICS","duration":"2 hr"},"MH4600":{"date":"4 May 2021","day":"Tuesday","time":"1.00 pm","code":"MH4600","name":"ALGEBRAIC TOPOLOGY","duration":"2 hr"},"MS4650":{"date":"4 May 2021","day":"Tuesday","time":"1.00 pm","code":"MS4650","name":"FUNCTIONAL NANOSTRUCTURE MATERIALS","duration":"2 hr"},"MT2005":{"date":"4 May 2021","day":"Tuesday","time":"1.00 pm","code":"MT2005","name":"PORT ECONOMICS","duration":"2 hr 30 min"},"CE4071":{"date":"4 May 2021","day":"Tuesday","time":"5.00 pm","code":"CE4071","name":"NETWORK SCIENCE","duration":"2 hr"},"CH4213":{"date":"4 May 2021","day":"Tuesday","time":"5.00 pm","code":"CH4213","name":"PHARMACOKINETICS & BIOPHARMACEUTICS","duration":"2 hr 30 min"},"CZ4071":{"date":"4 May 2021","day":"Tuesday","time":"5.00 pm","code":"CZ4071","name":"NETWORK SCIENCE","duration":"2 hr"},"EE8097":{"date":"4 May 2021","day":"Tuesday","time":"5.00 pm","code":"EE8097","name":"INTRODUCTION TO SPACECRAFT DESIGN","duration":"2 hr"},"EN1001":{"date":"4 May 2021","day":"Tuesday","time":"5.00 pm","code":"EN1001","name":"ENVIRONMENTAL CHEMISTRY","duration":"2 hr 30 min"},"HA3014":{"date":"4 May 2021","day":"Tuesday","time":"5.00 pm","code":"HA3014","name":"SINGAPORE'S FOREIGN POLICY","duration":"2 hr 30 min"},"HE3021":{"date":"4 May 2021","day":"Tuesday","time":"5.00 pm","code":"HE3021","name":"INTERMEDIATE ECONOMETRICS","duration":"2 hr 30 min"},"HP8005":{"date":"4 May 2021","day":"Tuesday","time":"5.00 pm","code":"HP8005","name":"INTRODUCTION TO HUMAN RESOURCE MANAGEMENT","duration":"2 hr"},"HT9102":{"date":"4 May 2021","day":"Tuesday","time":"5.00 pm","code":"HT9102","name":"LANGUAGE FOUNDATION FOR TRANSLATION","duration":"2 hr 30 min"},"MA4807":{"date":"4 May 2021","day":"Tuesday","time":"5.00 pm","code":"MA4807","name":"MARINE STRUCTURAL INTEGRITY","duration":"2 hr 30 min"},"MA4813":{"date":"4 May 2021","day":"Tuesday","time":"5.00 pm","code":"MA4813","name":"BUILDING SERVICES ENGINEERING","duration":"2 hr 30 min"},"MA4870":{"date":"4 May 2021","day":"Tuesday","time":"5.00 pm","code":"MA4870","name":"MECHANICS OF COMPOSITE MATERIALS","duration":"2 hr 30 min"},"MT1004":{"date":"4 May 2021","day":"Tuesday","time":"5.00 pm","code":"MT1004","name":"INTRODUCTION TO METEOROLOGY & OCEANOGRAPHY","duration":"2 hr 30 min"},"MT3005":{"date":"4 May 2021","day":"Tuesday","time":"5.00 pm","code":"MT3005","name":"QUALITY MANAGEMENT IN SHIPPING","duration":"2 hr 30 min"},"PS0002":{"date":"4 May 2021","day":"Tuesday","time":"5.00 pm","code":"PS0002","name":"INTRODUCTION TO DATA SCIENCE & ARTIFICIAL INTELLIGENCE","duration":"2 hr"},"SU2001":{"date":"4 May 2021","day":"Tuesday","time":"5.00 pm","code":"SU2001","name":"URBAN PLANNING & DESIGN","duration":"2 hr 30 min"},"BL9305":{"date":"5 May 2021","day":"Wednesday","time":"9.00 am","code":"BL9305","name":"ADVANCED TAXATION","duration":"2 hr 30 min"},"BS1006":{"date":"5 May 2021","day":"Wednesday","time":"9.00 am","code":"BS1006","name":"PRINCIPLES OF GENETICS","duration":"2 hr"},"CE2002":{"date":"5 May 2021","day":"Wednesday","time":"9.00 am","code":"CE2002","name":"OBJECT ORIENTED DESIGN & PROGRAMMING","duration":"2 hr"},"CE4055":{"date":"5 May 2021","day":"Wednesday","time":"9.00 am","code":"CE4055","name":"CYBER PHYSICAL SYSTEM SECURITY","duration":"2 hr"},"CM4033":{"date":"5 May 2021","day":"Wednesday","time":"9.00 am","code":"CM4033","name":"METAL MEDIATED REACTIONS","duration":"2 hr"},"CV2014":{"date":"5 May 2021","day":"Wednesday","time":"9.00 am","code":"CV2014","name":"GEOTECHNICAL ENGINEERING","duration":"2 hr 30 min"},"CZ2002":{"date":"5 May 2021","day":"Wednesday","time":"9.00 am","code":"CZ2002","name":"OBJECT ORIENTED DESIGN & PROGRAMMING","duration":"2 hr"},"CZ4055":{"date":"5 May 2021","day":"Wednesday","time":"9.00 am","code":"CZ4055","name":"CYBER PHYSICAL SYSTEM SECURITY","duration":"2 hr"},"EE3013":{"date":"5 May 2021","day":"Wednesday","time":"9.00 am","code":"EE3013","name":"SEMICONDUCTOR DEVICES & PROCESSING","duration":"2 hr"},"EE4285":{"date":"5 May 2021","day":"Wednesday","time":"9.00 am","code":"EE4285","name":"COMPUTATIONAL INTELLIGENCE","duration":"2 hr"},"EE4478":{"date":"5 May 2021","day":"Wednesday","time":"9.00 am","code":"EE4478","name":"DIGITAL VIDEO PROCESSING","duration":"2 hr"},"EE4840":{"date":"5 May 2021","day":"Wednesday","time":"9.00 am","code":"EE4840","name":"BIOPHOTONICS","duration":"2 hr"},"HE1004":{"date":"5 May 2021","day":"Wednesday","time":"9.00 am","code":"HE1004","name":"INTRODUCTION TO STATISTICAL THEORY & METHODS","duration":"2 hr 30 min"},"HL2032":{"date":"5 May 2021","day":"Wednesday","time":"9.00 am","code":"HL2032","name":"AFRICAN LITERATURE","duration":"2 hr 30 min"},"HS3014":{"date":"5 May 2021","day":"Wednesday","time":"9.00 am","code":"HS3014","name":"HEALTH, MEDICINE & SOCIETY","duration":"2 hr 30 min"},"IM4478":{"date":"5 May 2021","day":"Wednesday","time":"9.00 am","code":"IM4478","name":"DIGITAL VIDEO PROCESSING","duration":"2 hr"},"MA2002":{"date":"5 May 2021","day":"Wednesday","time":"9.00 am","code":"MA2002","name":"THEORY OF MECHANISM","duration":"2 hr 30 min"},"MA4871":{"date":"5 May 2021","day":"Wednesday","time":"9.00 am","code":"MA4871","name":"NON-DESTRUCTIVE TESTING","duration":"2 hr 30 min"},"MH1201":{"date":"5 May 2021","day":"Wednesday","time":"9.00 am","code":"MH1201","name":"LINEAR ALGEBRA II","duration":"2 hr"},"MS2018":{"date":"5 May 2021","day":"Wednesday","time":"9.00 am","code":"MS2018","name":"ELECTRONICS & MAGNETIC PROPERTIES OF MATERIALS","duration":"2 hr"},"MS4622":{"date":"5 May 2021","day":"Wednesday","time":"9.00 am","code":"MS4622","name":"COMPOSITE MATERIALS","duration":"2 hr"},"PH4603":{"date":"5 May 2021","day":"Wednesday","time":"9.00 am","code":"PH4603","name":"SOFT CONDENSED MATTER PHYSICS","duration":"2 hr"},"RE1018":{"date":"5 May 2021","day":"Wednesday","time":"9.00 am","code":"RE1018","name":"INTRODUCTORY THERMAL SCIENCES & ELECTROMAGNETISM","duration":"2 hr 30 min"},"BF3202":{"date":"5 May 2021","day":"Wednesday","time":"1.00 pm","code":"BF3202","name":"FIXED INCOME SECURITIES","duration":"2 hr 30 min"},"CE1011":{"date":"5 May 2021","day":"Wednesday","time":"1.00 pm","code":"CE1011","name":"ENGINEERING MATHEMATICS I","duration":"2 hr"},"CM2041":{"date":"5 May 2021","day":"Wednesday","time":"1.00 pm","code":"CM2041","name":"PHYSICAL & BIOPHYSICAL CHEMISTRY 1","duration":"2 hr"},"CS0205":{"date":"5 May 2021","day":"Wednesday","time":"1.00 pm","code":"CS0205","name":"BASIC MEDIA WRITING","duration":"2 hr"},"CV0001":{"date":"5 May 2021","day":"Wednesday","time":"1.00 pm","code":"CV0001","name":"CIVIL ENGINEERING & SUSTAINABLE BUILT ENVIRONMENT","duration":"2 hr 30 min"},"CZ1011":{"date":"5 May 2021","day":"Wednesday","time":"1.00 pm","code":"CZ1011","name":"ENGINEERING MATHEMATICS I","duration":"2 hr"},"EE3014":{"date":"5 May 2021","day":"Wednesday","time":"1.00 pm","code":"EE3014","name":"DIGITAL SIGNAL PROCESSING","duration":"2 hr"},"EE4105":{"date":"5 May 2021","day":"Wednesday","time":"1.00 pm","code":"EE4105","name":"CELLULAR COMMUNICATION SYSTEM DESIGN","duration":"2 hr"},"HC2050":{"date":"5 May 2021","day":"Wednesday","time":"1.00 pm","code":"HC2050","name":"CHINESE LEXICOLOGY","duration":"2 hr 30 min"},"HE4002":{"date":"5 May 2021","day":"Wednesday","time":"1.00 pm","code":"HE4002","name":"ADVANCED MACROECONOMICS","duration":"2 hr 30 min"},"HL3024":{"date":"5 May 2021","day":"Wednesday","time":"1.00 pm","code":"HL3024","name":"CONTEMPORARY WOMEN'S WRITING","duration":"2 hr 30 min"},"HP1100":{"date":"5 May 2021","day":"Wednesday","time":"1.00 pm","code":"HP1100","name":"FUNDAMENTALS OF SOCIAL SCIENCE RESEARCH","duration":"2 hr 30 min"},"IM3001":{"date":"5 May 2021","day":"Wednesday","time":"1.00 pm","code":"IM3001","name":"DIGITAL SIGNAL PROCESSING","duration":"2 hr"},"IM4105":{"date":"5 May 2021","day":"Wednesday","time":"1.00 pm","code":"IM4105","name":"CELLULAR COMMUNICATION SYSTEM DESIGN","duration":"2 hr"},"MA3002":{"date":"5 May 2021","day":"Wednesday","time":"1.00 pm","code":"MA3002","name":"SOLID MECHANICS & VIBRATION","duration":"2 hr 30 min"},"MA3700":{"date":"5 May 2021","day":"Wednesday","time":"1.00 pm","code":"MA3700","name":"AIRCRAFT STRUCTURES I","duration":"2 hr 30 min"},"MH1812":{"date":"5 May 2021","day":"Wednesday","time":"1.00 pm","code":"MH1812","name":"DISCRETE MATHEMATICS","duration":"2 hr"},"MH3511":{"date":"5 May 2021","day":"Wednesday","time":"1.00 pm","code":"MH3511","name":"DATA ANALYSIS WITH COMPUTER","duration":"2 hr"},"MS3013":{"date":"5 May 2021","day":"Wednesday","time":"1.00 pm","code":"MS3013","name":"ENVIRONMENTAL EFFECTS ON MATERIALS","duration":"2 hr"},"PH2101":{"date":"5 May 2021","day":"Wednesday","time":"1.00 pm","code":"PH2101","name":"QUANTUM MECHANICS 1","duration":"2 hr 30 min"},"BU8301":{"date":"5 May 2021","day":"Wednesday","time":"5.00 pm","code":"BU8301","name":"FUNDAMENTALS OF BUSINESS LAW","duration":"2 hr"},"CE4068":{"date":"5 May 2021","day":"Wednesday","time":"5.00 pm","code":"CE4068","name":"APPLICATION SECURITY","duration":"2 hr"},"CH2104":{"date":"5 May 2021","day":"Wednesday","time":"5.00 pm","code":"CH2104","name":"HEAT & MASS TRANSFER IN CHEMICAL & BIOLOGICAL SYSTEMS","duration":"2 hr 30 min"},"CH2114":{"date":"5 May 2021","day":"Wednesday","time":"5.00 pm","code":"CH2114","name":"HEAT & MASS TRANSFER IN CHEMICAL & BIOLOGICAL SYSTEMS","duration":"2 hr 30 min"},"CZ4068":{"date":"5 May 2021","day":"Wednesday","time":"5.00 pm","code":"CZ4068","name":"APPLICATION SECURITY","duration":"2 hr"},"EM9106":{"date":"5 May 2021","day":"Wednesday","time":"5.00 pm","code":"EM9106","name":"ENVIRONMENTAL IMPACT ASSESSMENT","duration":"2 hr 30 min"},"HP4104":{"date":"5 May 2021","day":"Wednesday","time":"5.00 pm","code":"HP4104","name":"EVIDENCE-BASED PRACTICE IN CLINICAL PSYCHOLOGY","duration":"2 hr 30 min"},"HP8006":{"date":"5 May 2021","day":"Wednesday","time":"5.00 pm","code":"HP8006","name":"PSYCHOLOGY OF CRISIS STRESS MANAGEMENT","duration":"2 hr"},"MA4808":{"date":"5 May 2021","day":"Wednesday","time":"5.00 pm","code":"MA4808","name":"MARINE CONTROL SYSTEMS","duration":"2 hr 30 min"},"MA4837":{"date":"5 May 2021","day":"Wednesday","time":"5.00 pm","code":"MA4837","name":"NET SHAPE MANUFACTURING","duration":"2 hr 30 min"},"MA4880":{"date":"5 May 2021","day":"Wednesday","time":"5.00 pm","code":"MA4880","name":"AIRPORT OPERATIONS & SYSTEMS","duration":"2 hr"},"AC2401":{"date":"6 May 2021","day":"Thursday","time":"9.00 am","code":"AC2401","name":"ACCOUNTING INFORMATION SYSTEMS","duration":"2 hr 30 min"},"BF2209":{"date":"6 May 2021","day":"Thursday","time":"9.00 am","code":"BF2209","name":"DERIVATIVE SECURITIES","duration":"2 hr 30 min"},"BS3008":{"date":"6 May 2021","day":"Thursday","time":"9.00 am","code":"BS3008","name":"COMPUTATIONAL BIOLOGY & MODELING","duration":"2 hr 30 min"},"CE2100":{"date":"6 May 2021","day":"Thursday","time":"9.00 am","code":"CE2100","name":"PROBABILITY & STATISTICS FOR COMPUTING","duration":"2 hr"},"CE4069":{"date":"6 May 2021","day":"Thursday","time":"9.00 am","code":"CE4069","name":"CONCEPTS & TECHNIQUES FOR MALWARE ANALYSIS","duration":"2 hr"},"CV8011":{"date":"6 May 2021","day":"Thursday","time":"9.00 am","code":"CV8011","name":"HUMAN RESOURCES MANAGEMENT & ENTREPRENEURSHIP","duration":"2 hr 30 min"},"CZ2100":{"date":"6 May 2021","day":"Thursday","time":"9.00 am","code":"CZ2100","name":"PROBABILITY & STATISTICS FOR COMPUTING","duration":"2 hr"},"CZ4069":{"date":"6 May 2021","day":"Thursday","time":"9.00 am","code":"CZ4069","name":"CONCEPTS & TECHNIQUES FOR MALWARE ANALYSIS","duration":"2 hr"},"HL4039":{"date":"6 May 2021","day":"Thursday","time":"9.00 am","code":"HL4039","name":"ADVANCED STUDIES IN CHILDREN'S LITERATURE","duration":"2 hr 30 min"},"HP3802":{"date":"6 May 2021","day":"Thursday","time":"9.00 am","code":"HP3802","name":"PERSONNEL PSYCHOLOGY","duration":"2 hr 30 min"},"MA3004":{"date":"6 May 2021","day":"Thursday","time":"9.00 am","code":"MA3004","name":"MATHEMATICAL METHODS IN ENGINEERING","duration":"2 hr 30 min"},"MA4831":{"date":"6 May 2021","day":"Thursday","time":"9.00 am","code":"MA4831","name":"COMPUTER-AIDED ENGINEERING","duration":"2 hr"},"MH1403":{"date":"6 May 2021","day":"Thursday","time":"9.00 am","code":"MH1403","name":"ALGORITHMS & COMPUTING","duration":"2 hr"},"MS2013":{"date":"6 May 2021","day":"Thursday","time":"9.00 am","code":"MS2013","name":"POLYMERS & COMPOSITES","duration":"2 hr"},"PH2301":{"date":"6 May 2021","day":"Thursday","time":"9.00 am","code":"PH2301","name":"PHYSICAL OPTICS","duration":"2 hr 30 min"},"BF3203":{"date":"6 May 2021","day":"Thursday","time":"1.00 pm","code":"BF3203","name":"EQUITY SECURITIES","duration":"2 hr 30 min"},"BF3212":{"date":"6 May 2021","day":"Thursday","time":"1.00 pm","code":"BF3212","name":"TRADE, STRUCTURED & SUPPLY CHAIN FINANCE","duration":"2 hr 30 min"},"BS4019":{"date":"6 May 2021","day":"Thursday","time":"1.00 pm","code":"BS4019","name":"DISCOVERY & DEVELOPMENT OF THERAPEUTIC ANTIBODIES","duration":"2 hr"},"CB1117":{"date":"6 May 2021","day":"Thursday","time":"1.00 pm","code":"CB1117","name":"ENGINEERING MATHEMATICS","duration":"2 hr 30 min"},"CE1012":{"date":"6 May 2021","day":"Thursday","time":"1.00 pm","code":"CE1012","name":"ENGINEERING MATHEMATICS II","duration":"2 hr"},"CE3007":{"date":"6 May 2021","day":"Thursday","time":"1.00 pm","code":"CE3007","name":"DIGITAL SIGNAL PROCESSING","duration":"2 hr"},"CM3031":{"date":"6 May 2021","day":"Thursday","time":"1.00 pm","code":"CM3031","name":"ORGANIC REACTION MECHANISMS & SYNTHESIS","duration":"2 hr"},"CV1011":{"date":"6 May 2021","day":"Thursday","time":"1.00 pm","code":"CV1011","name":"MECHANICS OF MATERIALS","duration":"2 hr 30 min"},"CZ1012":{"date":"6 May 2021","day":"Thursday","time":"1.00 pm","code":"CZ1012","name":"ENGINEERING MATHEMATICS II","duration":"2 hr"},"HP2400":{"date":"6 May 2021","day":"Thursday","time":"1.00 pm","code":"HP2400","name":"SOCIAL PSYCHOLOGY","duration":"2 hr 30 min"},"MA2003":{"date":"6 May 2021","day":"Thursday","time":"1.00 pm","code":"MA2003","name":"INTRODUCTION TO THERMO-FLUIDS","duration":"2 hr 30 min"},"MA8105":{"date":"6 May 2021","day":"Thursday","time":"1.00 pm","code":"MA8105","name":"ENGINEERING MANAGEMENT ANALYSIS","duration":"2 hr"},"MH3200":{"date":"6 May 2021","day":"Thursday","time":"1.00 pm","code":"MH3200","name":"ABSTRACT ALGEBRA I","duration":"2 hr"},"MH4512":{"date":"6 May 2021","day":"Thursday","time":"1.00 pm","code":"MH4512","name":"CLINICAL TRIALS","duration":"2 hr"},"MS1014":{"date":"6 May 2021","day":"Thursday","time":"1.00 pm","code":"MS1014","name":"MATERIALS CHEMISTRY II","duration":"2 hr"},"MS4013":{"date":"6 May 2021","day":"Thursday","time":"1.00 pm","code":"MS4013","name":"BIOMATERIALS","duration":"2 hr"},"MS4621":{"date":"6 May 2021","day":"Thursday","time":"1.00 pm","code":"MS4621","name":"POLYMER SCIENCE","duration":"1 hr"},"PH4401":{"date":"6 May 2021","day":"Thursday","time":"1.00 pm","code":"PH4401","name":"QUANTUM MECHANICS III","duration":"2 hr 30 min"}}